<?xml version="1.0" encoding="utf-8"?>
<scenario xmlns:xsd="http://www.w3.org/2001/XMLSchema" xmlns:xsi="http://www.w3.org/2001/XMLSchema-instance" id="MyScenario" label="MyScenario" version="5.16.0.0" xmlns="http://www.insa-rennes.fr/Xareus.Scenarios">
  <extendedInfo>
    <unityEditor xmlns="">
      <version>1.2</version>
    </unityEditor>
  </extendedInfo>
  <sequence xsi:type="SafePetriNet" id="Root" label="Root">
    <extendedInfo>
      <unityEditor xmlns="">
        <viewData x="0" y="0" zoom="1" />
        <comments />
        <sections />
      </unityEditor>
    </extendedInfo>
    <sequence xsi:type="Place" id="Place_0" label="Place_0">
      <extendedInfo>
        <unityEditor xmlns="">
          <position x="55" y="191" />
        </unityEditor>
      </extendedInfo>
    </sequence>
    <sequence xsi:type="Place" id="Place_1" label="Place_1">
      <extendedInfo>
        <unityEditor xmlns="">
          <position x="354" y="192" />
        </unityEditor>
      </extendedInfo>
    </sequence>
    <sequence xsi:type="Place" id="Place_2" label="Place_2">
      <extendedInfo>
        <unityEditor xmlns="">
          <position x="659" y="193" />
        </unityEditor>
      </extendedInfo>
    </sequence>
    <sequence xsi:type="Place" id="Place_3" label="Place_3">
      <extendedInfo>
        <unityEditor xmlns="">
          <position x="1160" y="200" />
        </unityEditor>
      </extendedInfo>
    </sequence>
    <transition id="Transition_0" label="Transition_0">
      <extendedInfo>
        <unityEditor xmlns="">
          <position x="227" y="196" />
        </unityEditor>
      </extendedInfo>
      <event id="Transition_0" label="Transition_0">
        <sensorCheck classname="MoveArmSensor,Assembly-CSharp">
          <extendedInfo>
            <unityEditor xmlns="">
              <editBox type="Xareus.Unity.Editor.Scenarios.UI.DefaultEditBox,Xareus.Unity.Editor" />
            </unityEditor>
          </extendedInfo>
          <param type="UnityEngine.GameObject,UnityEngine.CoreModule" name="Arms to follow">
            <extendedInfo>
              <unityEditor xmlns="">
                <field type="Xareus.Unity.Editor.Scenarios.UI.Fields.ObjectDropField`1[[UnityEngine.GameObject,UnityEngine.CoreModule]],Xareus.Unity.Editor" />
              </unityEditor>
            </extendedInfo>
            <param value="" type="System.Guid,mscorlib" name="UFID" />
          </param>
          <param type="System.String,mscorlib" name="Parameter">
            <extendedInfo>
              <unityEditor xmlns="">
                <field type="Xareus.Unity.Editor.Scenarios.UI.Fields.StringField,Xareus.Unity.Editor" />
              </unityEditor>
            </extendedInfo>
          </param>
          <param value="False" type="System.Boolean,mscorlib" name="TrackPosition">
            <extendedInfo>
              <unityEditor xmlns="">
                <field type="Xareus.Unity.Editor.Scenarios.UI.Fields.BoolField,Xareus.Unity.Editor" />
              </unityEditor>
            </extendedInfo>
          </param>
          <param value="False" type="System.Boolean,mscorlib" name="SmoothPosition">
            <extendedInfo>
              <unityEditor xmlns="">
                <field type="Xareus.Unity.Editor.Scenarios.UI.Fields.BoolField,Xareus.Unity.Editor" />
              </unityEditor>
            </extendedInfo>
          </param>
          <param value="False" type="System.Boolean,mscorlib" name="ThrowSmoothDuration">
            <extendedInfo>
              <unityEditor xmlns="">
                <field type="Xareus.Unity.Editor.Scenarios.UI.Fields.BoolField,Xareus.Unity.Editor" />
              </unityEditor>
            </extendedInfo>
          </param>
        </sensorCheck>
        <effectorUpdate classname="MoveControllerEffector,Assembly-CSharp">
          <extendedInfo>
            <unityEditor xmlns="">
              <editBox type="Xareus.Unity.Editor.Scenarios.UI.DefaultEditBox,Xareus.Unity.Editor" />
            </unityEditor>
          </extendedInfo>
          <param type="System.String,mscorlib" name="Parameter">
            <extendedInfo>
              <unityEditor xmlns="">
                <field type="Xareus.Unity.Editor.Scenarios.UI.Fields.StringField,Xareus.Unity.Editor" />
              </unityEditor>
            </extendedInfo>
          </param>
          <param value="0" type="System.Int32,mscorlib" name="ParameterInt">
            <extendedInfo>
              <unityEditor xmlns="">
                <field type="Xareus.Unity.Editor.Scenarios.UI.Fields.IntField,Xareus.Unity.Editor" />
              </unityEditor>
            </extendedInfo>
          </param>
          <param type="System.String,mscorlib" name="gameObjectToObserve">
            <extendedInfo>
              <unityEditor xmlns="">
                <field type="Xareus.Unity.Editor.Scenarios.UI.Fields.StringField,Xareus.Unity.Editor" />
              </unityEditor>
            </extendedInfo>
          </param>
        </effectorUpdate>
      </event>
      <upstreamSequence idref="Place_0" />
      <downstreamSequence idref="Place_1" />
    </transition>
    <transition id="Transition_1" label="Transition_1">
      <extendedInfo>
        <unityEditor xmlns="">
          <position x="517" y="194.5" />
        </unityEditor>
      </extendedInfo>
      <event id="Transition_1" label="Transition_1">
        <effectorUpdate classname="ClickEffector,Assembly-CSharp">
          <extendedInfo>
            <unityEditor xmlns="">
              <editBox type="Xareus.Unity.Editor.Scenarios.UI.DefaultEditBox,Xareus.Unity.Editor" />
            </unityEditor>
          </extendedInfo>
          <param type="System.String,mscorlib" name="gameObjectToObserve">
            <extendedInfo>
              <unityEditor xmlns="">
                <field type="Xareus.Unity.Editor.Scenarios.UI.Fields.StringField,Xareus.Unity.Editor" />
              </unityEditor>
            </extendedInfo>
          </param>
          <param type="System.String,mscorlib" name="ControllerHand">
            <extendedInfo>
              <unityEditor xmlns="">
                <field type="Xareus.Unity.Editor.Scenarios.UI.Fields.StringField,Xareus.Unity.Editor" />
              </unityEditor>
            </extendedInfo>
          </param>
          <param type="System.String,mscorlib" name="ButtonToSimulate">
            <extendedInfo>
              <unityEditor xmlns="">
                <field type="Xareus.Unity.Editor.Scenarios.UI.Fields.StringField,Xareus.Unity.Editor" />
              </unityEditor>
            </extendedInfo>
          </param>
        </effectorUpdate>
      </event>
      <upstreamSequence idref="Place_1" />
      <downstreamSequence idref="Place_2" />
    </transition>
    <transition id="Transition_2" label="Transition_2">
      <extendedInfo>
        <unityEditor xmlns="">
          <position x="845.5" y="189" />
        </unityEditor>
      </extendedInfo>
      <event id="Transition_2" label="Transition_2">
        <effectorUpdate classname="UnclickEffector,Assembly-CSharp">
          <extendedInfo>
            <unityEditor xmlns="">
              <editBox type="Xareus.Unity.Editor.Scenarios.UI.DefaultEditBox,Xareus.Unity.Editor" />
            </unityEditor>
          </extendedInfo>
          <param type="System.String,mscorlib" name="ControllerHand">
            <extendedInfo>
              <unityEditor xmlns="">
                <field type="Xareus.Unity.Editor.Scenarios.UI.Fields.StringField,Xareus.Unity.Editor" />
              </unityEditor>
            </extendedInfo>
          </param>
          <param type="System.String,mscorlib" name="ButtonToSimulate">
            <extendedInfo>
              <unityEditor xmlns="">
                <field type="Xareus.Unity.Editor.Scenarios.UI.Fields.StringField,Xareus.Unity.Editor" />
              </unityEditor>
            </extendedInfo>
          </param>
        </effectorUpdate>
      </event>
      <upstreamSequence idref="Place_2" />
      <downstreamSequence idref="Place_3" />
    </transition>
    <transition id="Transition_4" label="Transition_4">
      <extendedInfo>
        <unityEditor xmlns="">
          <position x="613.5" y="489" />
        </unityEditor>
      </extendedInfo>
      <event id="Transition_4" label="Transition_4" />
      <upstreamSequence idref="Place_0" />
      <downstreamSequence idref="Place_3" />
    </transition>
    <transition id="Transition_3" label="Transition_3">
      <extendedInfo>
        <unityEditor xmlns="">
          <position x="740" y="300" />
        </unityEditor>
      </extendedInfo>
      <event id="Transition_3" label="Transition_3" />
      <upstreamSequence idref="Place_3" />
      <downstreamSequence idref="Place_1" />
    </transition>
    <finalSequence idref="Place_3" />
  </sequence>
</scenario>